litellm_enterprise/__init__.py
litellm_enterprise/enterprise_callbacks/callback_controls.py
litellm_enterprise/enterprise_callbacks/example_logging_api.py
litellm_enterprise/enterprise_callbacks/llama_guard.py
litellm_enterprise/enterprise_callbacks/llm_guard.py
litellm_enterprise/enterprise_callbacks/pagerduty/pagerduty.py
litellm_enterprise/enterprise_callbacks/secret_detection.py
litellm_enterprise/enterprise_callbacks/secrets_plugins/__init__.py
litellm_enterprise/enterprise_callbacks/secrets_plugins/adafruit.py
litellm_enterprise/enterprise_callbacks/secrets_plugins/adobe.py
litellm_enterprise/enterprise_callbacks/secrets_plugins/age_secret_key.py
litellm_enterprise/enterprise_callbacks/secrets_plugins/airtable_api_key.py
litellm_enterprise/enterprise_callbacks/secrets_plugins/algolia_api_key.py
litellm_enterprise/enterprise_callbacks/secrets_plugins/alibaba.py
litellm_enterprise/enterprise_callbacks/secrets_plugins/asana.py
litellm_enterprise/enterprise_callbacks/secrets_plugins/atlassian_api_token.py
litellm_enterprise/enterprise_callbacks/secrets_plugins/authress_access_key.py
litellm_enterprise/enterprise_callbacks/secrets_plugins/beamer_api_token.py
litellm_enterprise/enterprise_callbacks/secrets_plugins/bitbucket.py
litellm_enterprise/enterprise_callbacks/secrets_plugins/bittrex.py
litellm_enterprise/enterprise_callbacks/secrets_plugins/clojars_api_token.py
litellm_enterprise/enterprise_callbacks/secrets_plugins/codecov_access_token.py
litellm_enterprise/enterprise_callbacks/secrets_plugins/coinbase_access_token.py
litellm_enterprise/enterprise_callbacks/secrets_plugins/confluent.py
litellm_enterprise/enterprise_callbacks/secrets_plugins/contentful_api_token.py
litellm_enterprise/enterprise_callbacks/secrets_plugins/databricks_api_token.py
litellm_enterprise/enterprise_callbacks/secrets_plugins/datadog_access_token.py
litellm_enterprise/enterprise_callbacks/secrets_plugins/defined_networking_api_token.py
litellm_enterprise-0.1.27.dist-info/METADATA
litellm_enterprise-0.1.27.dist-info/WHEEL
litellm_enterprise-0.1.27.dist-info/licenses/LICENSE.md
litellm_enterprise-0.1.27.dist-info/RECORD
